{"team":"CAR","season":2005,"players":[{"id":"00-0011411","name":"Jeff Mitchell","position":"C","number":"60","unit":"Offense"},{"id":"00-0019100","name":"Brad Hoover","position":"FB","number":"45","unit":"Offense"},{"id":"00-0023514","name":"Evan Mathis","position":"G","number":"71","unit":"Offense"},{"id":"00-0023602","name":"Geoff Hangartner","position":"G","number":"63","unit":"Offense"},{"id":"00-0016990","name":"Mike Wahle","position":"G","number":"68","unit":"Offense"},{"id":"00-0019597","name":"Tutan Reyes","position":"G","number":"76","unit":"Offense"},{"id":"00-0020434","name":"Chris Weinke","position":"QB","number":"16","unit":"Offense"},{"id":"00-0004161","name":"Jake Delhomme","position":"QB","number":"17","unit":"Offense"},{"id":"00-0023555","name":"Stefan LeFors","position":"QB","number":"3","unit":"Offense"},{"id":"00-0021164","name":"DeShaun Foster","position":"RB","number":"26","unit":"Offense"},{"id":"00-0020587","name":"Jamal Robertson","position":"RB","number":"22","unit":"Offense"},{"id":"00-0019831","name":"Nick Goings","position":"RB","number":"37","unit":"Offense"},{"id":"00-0019453","name":"Rod Smart","position":"RB","number":"32","unit":"Offense"},{"id":"00-0004052","name":"Stephen Davis","position":"RB","number":"48","unit":"Offense"},{"id":"00-0020218","name":"Dave Kadela","position":"T","number":"61","unit":"Offense"},{"id":"00-0022117","name":"Jordan Gross","position":"T","number":"69","unit":"Offense"},{"id":"00-0005432","name":"Todd Fordham","position":"T","number":"78","unit":"Offense"},{"id":"00-0022214","name":"Travelle Wharton","position":"T","number":"70","unit":"Offense"},{"id":"00-0022886","name":"Casey Cramer","position":"TE","number":"49","unit":"Offense"},{"id":"00-0010333","name":"Kris Mangum","position":"TE","number":"86","unit":"Offense"},{"id":"00-0022706","name":"Michael Gaines","position":"TE","number":"84","unit":"Offense"},{"id":"00-0022129","name":"Mike Seidman","position":"TE","number":"82","unit":"Offense"},{"id":"00-0022879","name":"Drew Carter","position":"WR","number":"18","unit":"Offense"},{"id":"00-0023262","name":"Efrem Hill","position":"WR","number":"5","unit":"Offense"},{"id":"00-0006777","name":"Karl Hankton","position":"WR","number":"88","unit":"Offense"},{"id":"00-0022726","name":"Keary Colbert","position":"WR","number":"83","unit":"Offense"},{"id":"00-0013268","name":"Ricky Proehl","position":"WR","number":"81","unit":"Offense"},{"id":"00-0020525","name":"Rod Gardner","position":"WR","number":"87","unit":"Offense"},{"id":"00-0020337","name":"Steve Smith","position":"WR","number":"89","unit":"Offense"},{"id":"00-0022914","name":"Chris Gamble","position":"CB","number":"20","unit":"Defense"},{"id":"00-0021224","name":"Dante Wesley","position":"CB","number":"21","unit":"Defense"},{"id":"00-0022260","name":"Garnell Wilds","position":"CB","number":"38","unit":"Defense"},{"id":"00-0023221","name":"Jermaine Hardy","position":"CB","number":"29","unit":"Defense"},{"id":"00-0020499","name":"Ken Lucas","position":"CB","number":"23","unit":"Defense"},{"id":"00-0021900","name":"Ricky Manning","position":"CB","number":"24","unit":"Defense"},{"id":"00-0023692","name":"Billy Parker","position":"DB","number":"31","unit":"Defense"},{"id":"00-0017077","name":"Al Wallace","position":"DE","number":"96","unit":"Defense"},{"id":"00-0023622","name":"Jovan Haye","position":"DE","number":"92","unit":"Defense"},{"id":"00-0021140","name":"Julius Peppers","position":"DE","number":"90","unit":"Defense"},{"id":"00-0021001","name":"Kemp Rasmussen","position":"DE","number":"97","unit":"Defense"},{"id":"00-0014132","name":"Mike Rucker","position":"DE","number":"93","unit":"Defense"},{"id":"00-0023524","name":"Atiyyah Ellison","position":"DT","number":"98","unit":"Defense"},{"id":"00-0002186","name":"Brentson Buckner","position":"DT","number":"99","unit":"Defense"},{"id":"00-0022356","name":"Jordan Carstens","position":"DT","number":"67","unit":"Defense"},{"id":"00-0022146","name":"Kindal Moorehead","position":"DT","number":"94","unit":"Defense"},{"id":"00-0020380","name":"Kris Jenkins","position":"DT","number":"77","unit":"Defense"},{"id":"00-0020468","name":"Idrees Bashir","position":"FS","number":"33","unit":"Defense"},{"id":"00-0011372","name":"Mike Minter","position":"FS","number":"30","unit":"Defense"},{"id":"00-0022220","name":"Sean Tufts","position":"LB","number":"57","unit":"Defense"},{"id":"00-0023582","name":"Adam Seward","position":"MLB","number":"59","unit":"Defense"},{"id":"00-0020443","name":"Dan Morgan","position":"MLB","number":"55","unit":"Defense"},{"id":"00-0021493","name":"Vinny Ciurciu","position":"MLB","number":"50","unit":"Defense"},{"id":"00-0019669","name":"Brandon Short","position":"OLB","number":"53","unit":"Defense"},{"id":"00-0004505","name":"Chris Draft","position":"OLB","number":"52","unit":"Defense"},{"id":"00-0021085","name":"Will Witherspoon","position":"OLB","number":"54","unit":"Defense"},{"id":"00-0020280","name":"Marlon McCree","position":"SS","number":"27","unit":"Defense"},{"id":"00-0023448","name":"Thomas Davis","position":"SS","number":"47","unit":"Defense"},{"id":"00-0009028","name":"John Kasay","position":"K","number":"4","unit":"Special Teams"},{"id":"00-0009530","name":"Jason Kyle","position":"LS","number":"56","unit":"Special Teams"},{"id":"00-0019921","name":"Jason Baker","position":"P","number":"7","unit":"Special Teams"}]}