{"team":"CIN","season":2009,"players":[{"id":"00-0027075","name":"Jonathan Luigs","position":"C","number":"50","unit":"Offense"},{"id":"00-0024670","name":"Kyle Cook","position":"C","number":"64","unit":"Offense"},{"id":"00-0022141","name":"Jeremi Johnson","position":"FB","number":"23","unit":"Offense"},{"id":"00-0019629","name":"Bobbie Williams","position":"G","number":"63","unit":"Offense"},{"id":"00-0023514","name":"Evan Mathis","position":"G","number":"66","unit":"Offense"},{"id":"00-0023958","name":"Nate Livings","position":"G","number":"62","unit":"Offense"},{"id":"00-0021429","name":"Carson Palmer","position":"QB","number":"9","unit":"Offense"},{"id":"00-0021296","name":"J.T. O'Sullivan","position":"QB","number":"4","unit":"Offense"},{"id":"00-0025592","name":"Jordan Palmer","position":"QB","number":"5","unit":"Offense"},{"id":"00-0026941","name":"Bernard Scott","position":"RB","number":"28","unit":"Offense"},{"id":"00-0025439","name":"Brian Leonard","position":"RB","number":"40","unit":"Offense"},{"id":"00-0023439","name":"Cedric Benson","position":"RB","number":"32","unit":"Offense"},{"id":"00-0027143","name":"Fui Vakapuna","position":"RB","number":"37","unit":"Offense"},{"id":"00-0021976","name":"Larry Johnson","position":"RB","number":"27","unit":"Offense"},{"id":"00-0026982","name":"Andre Smith","position":"T","number":"71","unit":"Offense"},{"id":"00-0024270","name":"Andrew Whitworth","position":"T","number":"77","unit":"Offense"},{"id":"00-0026252","name":"Anthony Collins","position":"T","number":"73","unit":"Offense"},{"id":"00-0023920","name":"Dennis Roland","position":"T","number":"74","unit":"Offense"},{"id":"00-0027069","name":"Chase Coffman","position":"TE","number":"80","unit":"Offense"},{"id":"00-0024607","name":"Daniel Coats","position":"TE","number":"86","unit":"Offense"},{"id":"00-0026809","name":"Darius Hill","position":"TE","number":"49","unit":"Offense"},{"id":"00-0022484","name":"J.P. Foschi","position":"TE","number":"88","unit":"Offense"},{"id":"00-0026237","name":"Andre Caldwell","position":"WR","number":"87","unit":"Offense"},{"id":"00-0020397","name":"Chad Ochocinco","position":"WR","number":"85","unit":"Offense"},{"id":"00-0023518","name":"Chris Henry","position":"WR","number":"15","unit":"Offense"},{"id":"00-0026186","name":"Jerome Simpson","position":"WR","number":"89","unit":"Offense"},{"id":"00-0018958","name":"Laveranues Coles","position":"WR","number":"11","unit":"Offense"},{"id":"00-0026396","name":"Maurice Purify","position":"WR","number":"14","unit":"Offense"},{"id":"00-0026716","name":"Quan Cosby","position":"WR","number":"12","unit":"Offense"},{"id":"00-0025532","name":"David Jones","position":"CB","number":"20","unit":"Defense"},{"id":"00-0024638","name":"Geoffrey Pope","position":"CB","number":"24","unit":"Defense"},{"id":"00-0024239","name":"Johnathan Joseph","position":"CB","number":"22","unit":"Defense"},{"id":"00-0022928","name":"Keiwan Ratliff","position":"CB","number":"26","unit":"Defense"},{"id":"00-0025405","name":"Leon Hall","position":"CB","number":"29","unit":"Defense"},{"id":"00-0026928","name":"Morgan Trent","position":"CB","number":"25","unit":"Defense"},{"id":"00-0026720","name":"Rico Murray","position":"DB","number":"44","unit":"Defense"},{"id":"00-0022918","name":"Antwan Odom","position":"DE","number":"98","unit":"Defense"},{"id":"00-0024306","name":"Frostee Rucker","position":"DE","number":"92","unit":"Defense"},{"id":"00-0027044","name":"Michael Johnson","position":"DE","number":"93","unit":"Defense"},{"id":"00-0022867","name":"Robert Geathers","position":"DE","number":"91","unit":"Defense"},{"id":"00-0024338","name":"Domata Peko","position":"DT","number":"94","unit":"Defense"},{"id":"00-0023665","name":"Jonathan Fanene","position":"DT","number":"68","unit":"Defense"},{"id":"00-0024347","name":"Orien Harris","position":"DT","number":"95","unit":"Defense"},{"id":"00-0026217","name":"Pat Sims","position":"DT","number":"90","unit":"Defense"},{"id":"00-0022696","name":"Tank Johnson","position":"DT","number":"99","unit":"Defense"},{"id":"00-0022167","name":"Chris Crocker","position":"FS","number":"42","unit":"Defense"},{"id":"00-0026721","name":"Tom Nelson","position":"FS","number":"43","unit":"Defense"},{"id":"00-0026725","name":"Dan Skuta","position":"LB","number":"51","unit":"Defense"},{"id":"00-0024282","name":"Abdul Hodge","position":"MLB","number":"52","unit":"Defense"},{"id":"00-0019635","name":"Dhani Jones","position":"MLB","number":"57","unit":"Defense"},{"id":"00-0021679","name":"Shaun Smith","position":"NT","number":"96","unit":"Defense"},{"id":"00-0024356","name":"Brandon Johnson","position":"OLB","number":"59","unit":"Defense"},{"id":"00-0026149","name":"Keith Rivers","position":"OLB","number":"55","unit":"Defense"},{"id":"00-0023729","name":"Rashad Jeanty","position":"OLB","number":"53","unit":"Defense"},{"id":"00-0027014","name":"Rey Maualuga","position":"OLB","number":"58","unit":"Defense"},{"id":"00-0025640","name":"Chinedum Ndukwe","position":"SS","number":"41","unit":"Defense"},{"id":"00-0020678","name":"Kyries Hebert","position":"SS","number":"34","unit":"Defense"},{"id":"00-0021143","name":"Roy Williams","position":"SS","number":"31","unit":"Defense"},{"id":"00-0019536","name":"Shayne Graham","position":"K","number":"17","unit":"Special Teams"},{"id":"00-0025630","name":"Clark Harris","position":"LS","number":"46","unit":"Special Teams"},{"id":"00-0027103","name":"Kevin Huber","position":"P","number":"10","unit":"Special Teams"}]}