{"team":"MIN","season":2009,"players":[{"id":"00-0026327","name":"John Sullivan","position":"C","number":"65","unit":"Offense"},{"id":"00-0026580","name":"Jon Cooper","position":"C","number":"68","unit":"Offense"},{"id":"00-0023774","name":"Naufahu Tahi","position":"FB","number":"38","unit":"Offense"},{"id":"00-0022266","name":"Anthony Herrera","position":"G","number":"64","unit":"Offense"},{"id":"00-0020466","name":"Steve Hutchinson","position":"G","number":"76","unit":"Offense"},{"id":"00-0005106","name":"Brett Favre","position":"QB","number":"4","unit":"Offense"},{"id":"00-0020480","name":"Sage Rosenfels","position":"QB","number":"2","unit":"Offense"},{"id":"00-0024279","name":"Tarvaris Jackson","position":"QB","number":"7","unit":"Offense"},{"id":"00-0025394","name":"Adrian Peterson","position":"RB","number":"28","unit":"Offense"},{"id":"00-0025955","name":"Albert Young","position":"RB","number":"34","unit":"Offense"},{"id":"00-0021314","name":"Chester Taylor","position":"RB","number":"29","unit":"Offense"},{"id":"00-0020801","name":"Artis Hicks","position":"T","number":"79","unit":"Offense"},{"id":"00-0021383","name":"Bryant McKinnie","position":"T","number":"74","unit":"Offense"},{"id":"00-0027030","name":"Phil Loadholt","position":"T","number":"71","unit":"Offense"},{"id":"00-0024266","name":"Ryan Cook","position":"T","number":"62","unit":"Offense"},{"id":"00-0024321","name":"Garrett Mills","position":"TE","number":"45","unit":"Offense"},{"id":"00-0022746","name":"Jeff Dugan","position":"TE","number":"83","unit":"Offense"},{"id":"00-0009323","name":"Jim Kleinsasser","position":"TE","number":"40","unit":"Offense"},{"id":"00-0022054","name":"Visanthe Shiancoe","position":"TE","number":"81","unit":"Offense"},{"id":"00-0022807","name":"Bernard Berrian","position":"WR","number":"87","unit":"Offense"},{"id":"00-0025951","name":"Darius Reynaud","position":"WR","number":"82","unit":"Offense"},{"id":"00-0021508","name":"Greg Lewis","position":"WR","number":"17","unit":"Offense"},{"id":"00-0026333","name":"Jaymar Johnson","position":"WR","number":"11","unit":"Offense"},{"id":"00-0026998","name":"Percy Harvin","position":"WR","number":"12","unit":"Offense"},{"id":"00-0025431","name":"Sidney Rice","position":"WR","number":"18","unit":"Offense"},{"id":"00-0018093","name":"Antoine Winfield","position":"CB","number":"26","unit":"Defense"},{"id":"00-0027058","name":"Asher Allen","position":"CB","number":"21","unit":"Defense"},{"id":"00-0022352","name":"Benny Sapp","position":"CB","number":"22","unit":"Defense"},{"id":"00-0024263","name":"Cedric Griffin","position":"CB","number":"23","unit":"Defense"},{"id":"00-0023511","name":"Karl Paymah","position":"CB","number":"41","unit":"Defense"},{"id":"00-0025489","name":"Brian Robison","position":"DE","number":"96","unit":"Defense"},{"id":"00-0022740","name":"Jared Allen","position":"DE","number":"69","unit":"Defense"},{"id":"00-0023893","name":"Jayme Mitchell","position":"DE","number":"92","unit":"Defense"},{"id":"00-0024342","name":"Ray Edwards","position":"DE","number":"91","unit":"Defense"},{"id":"00-0022073","name":"Kevin Williams","position":"DT","number":"93","unit":"Defense"},{"id":"00-0026292","name":"Letroy Guion","position":"DT","number":"98","unit":"Defense"},{"id":"00-0025940","name":"Husain Abdullah","position":"FS","number":"39","unit":"Defense"},{"id":"00-0022842","name":"Madieu Williams","position":"FS","number":"20","unit":"Defense"},{"id":"00-0025948","name":"Jeremy Leman","position":"LB","number":"57","unit":"Defense"},{"id":"00-0022081","name":"E.J. Henderson","position":"MLB","number":"56","unit":"Defense"},{"id":"00-0027108","name":"Jasper Brinkley","position":"MLB","number":"54","unit":"Defense"},{"id":"00-0024426","name":"Fred Evans","position":"NT","number":"90","unit":"Defense"},{"id":"00-0022155","name":"Jimmy Kennedy","position":"NT","number":"73","unit":"Defense"},{"id":"00-0017899","name":"Pat Williams","position":"NT","number":"94","unit":"Defense"},{"id":"00-0021197","name":"Ben Leber","position":"OLB","number":"51","unit":"Defense"},{"id":"00-0024232","name":"Chad Greenway","position":"OLB","number":"52","unit":"Defense"},{"id":"00-0025945","name":"Erin Henderson","position":"OLB","number":"50","unit":"Defense"},{"id":"00-0023215","name":"Heath Farwell","position":"OLB","number":"59","unit":"Defense"},{"id":"00-0026486","name":"Kenny Onatolu","position":"OLB","number":"55","unit":"Defense"},{"id":"00-0025552","name":"Eric Frampton","position":"SS","number":"37","unit":"Defense"},{"id":"00-0026952","name":"Jamarca Sanford","position":"SS","number":"33","unit":"Defense"},{"id":"00-0026183","name":"Tyrell Johnson","position":"SS","number":"25","unit":"Defense"},{"id":"00-0010072","name":"Ryan Longwell","position":"K","number":"8","unit":"Special Teams"},{"id":"00-0022581","name":"Cullen Loeffler","position":"LS","number":"46","unit":"Special Teams"},{"id":"00-0023060","name":"Chris Kluwe","position":"P","number":"5","unit":"Special Teams"}]}