{"team":"NYG","season":2015,"players":[{"id":"00-0026574","name":"Dallas Reynolds","position":"C","number":"61","unit":"Offense"},{"id":"00-0031238","name":"Weston Richburg","position":"C","number":"70","unit":"Offense"},{"id":"00-0030785","name":"Nikita Whitlock","position":"FB","number":"49","unit":"Offense"},{"id":"00-0029139","name":"Adam Gettis","position":"G","number":"60","unit":"Offense"},{"id":"00-0026381","name":"Geoff Schwartz","position":"G","number":"74","unit":"Offense"},{"id":"00-0027678","name":"John Jerry","position":"G","number":"77","unit":"Offense"},{"id":"00-0030585","name":"Justin Pugh","position":"G","number":"67","unit":"Offense"},{"id":"00-0022803","name":"Eli Manning","position":"QB","number":"10","unit":"Offense"},{"id":"00-0030586","name":"Ryan Nassib","position":"QB","number":"12","unit":"Offense"},{"id":"00-0031055","name":"Andre Williams","position":"RB","number":"44","unit":"Offense"},{"id":"00-0030860","name":"Orleans Darkwa","position":"RB","number":"26","unit":"Offense"},{"id":"00-0027155","name":"Rashad Jennings","position":"RB","number":"23","unit":"Offense"},{"id":"00-0027994","name":"Shane Vereen","position":"RB","number":"34","unit":"Offense"},{"id":"00-0031622","name":"Bobby Hart","position":"T","number":"68","unit":"Offense"},{"id":"00-0029821","name":"Emmett Cleary","position":"T","number":"63","unit":"Offense"},{"id":"00-0032259","name":"Ereck Flowers","position":"T","number":"76","unit":"Offense"},{"id":"00-0027768","name":"Marshall Newhouse","position":"T","number":"73","unit":"Offense"},{"id":"00-0023752","name":"Daniel Fells","position":"TE","number":"85","unit":"Offense"},{"id":"00-0031462","name":"Jerome Cunningham","position":"TE","number":"86","unit":"Offense"},{"id":"00-0028838","name":"Larry Donnell","position":"TE","number":"84","unit":"Offense"},{"id":"00-0031744","name":"Matt LaCosse","position":"TE","number":"81","unit":"Offense"},{"id":"00-0032004","name":"Will Tye","position":"TE","number":"45","unit":"Offense"},{"id":"00-0032001","name":"Ben Edwards","position":"WR","number":"83","unit":"Offense"},{"id":"00-0028114","name":"Dwayne Harris","position":"WR","number":"17","unit":"Offense"},{"id":"00-0031953","name":"Geremy Davis","position":"WR","number":"18","unit":"Offense"},{"id":"00-0027005","name":"Hakeem Nicks","position":"WR","number":"88","unit":"Offense"},{"id":"00-0030274","name":"Myles White","position":"WR","number":"19","unit":"Offense"},{"id":"00-0031235","name":"Odell Beckham","position":"WR","number":"13","unit":"Offense"},{"id":"00-0029262","name":"Rueben Randle","position":"WR","number":"82","unit":"Offense"},{"id":"00-0027265","name":"Victor Cruz","position":"WR","number":"80","unit":"Offense"},{"id":"00-0030535","name":"Brandon McGee","position":"CB","number":"33","unit":"Defense"},{"id":"00-0026156","name":"Dominique Rodgers-Cromartie","position":"CB","number":"41","unit":"Defense"},{"id":"00-0029267","name":"Jayron Hosley","position":"CB","number":"28","unit":"Defense"},{"id":"00-0030556","name":"Leon McFadden","position":"CB","number":"37","unit":"Defense"},{"id":"00-0027957","name":"Prince Amukamara","position":"CB","number":"20","unit":"Defense"},{"id":"00-0029314","name":"Trevin Wade","position":"CB","number":"31","unit":"Defense"},{"id":"00-0025608","name":"Trumaine McBride","position":"CB","number":"38","unit":"Defense"},{"id":"00-0030695","name":"Tramain Jacobs","position":"DB","number":"25","unit":"Defense"},{"id":"00-0032284","name":"Brad Bars","position":"DE","number":"66","unit":"Defense"},{"id":"00-0021706","name":"Cullen Jenkins","position":"DE","number":"99","unit":"Defense"},{"id":"00-0030069","name":"Damontre Moore","position":"DE","number":"98","unit":"Defense"},{"id":"00-0027818","name":"George Selvie","position":"DE","number":"93","unit":"Defense"},{"id":"00-0027867","name":"Jason Pierre-Paul","position":"DE","number":"90","unit":"Defense"},{"id":"00-0030776","name":"Kerry Wynn","position":"DE","number":"72","unit":"Defense"},{"id":"00-0031562","name":"Owamagbe Odighizuwa","position":"DE","number":"58","unit":"Defense"},{"id":"00-0026994","name":"Robert Ayers","position":"DE","number":"91","unit":"Defense"},{"id":"00-0030425","name":"Stansly Maponga","position":"DE","number":"71","unit":"Defense"},{"id":"00-0031403","name":"Jay Bromley","position":"DT","number":"96","unit":"Defense"},{"id":"00-0030063","name":"Johnathan Hankins","position":"DT","number":"95","unit":"Defense"},{"id":"00-0029312","name":"Markus Kuhn","position":"DT","number":"78","unit":"Defense"},{"id":"00-0030082","name":"Montori Hughes","position":"DT","number":"79","unit":"Defense"},{"id":"00-0025411","name":"Brandon Meriweather","position":"FS","number":"22","unit":"Defense"},{"id":"00-0032262","name":"Landon Collins","position":"FS","number":"21","unit":"Defense"},{"id":"00-0030508","name":"Nico Johnson","position":"ILB","number":"48","unit":"Defense"},{"id":"00-0031155","name":"James Morris","position":"LB","number":"46","unit":"Defense"},{"id":"00-0027108","name":"Jasper Brinkley","position":"MLB","number":"53","unit":"Defense"},{"id":"00-0025412","name":"Jon Beason","position":"MLB","number":"52","unit":"Defense"},{"id":"00-0031480","name":"Uani 'Unga","position":"MLB","number":"47","unit":"Defense"},{"id":"00-0024339","name":"Barry Cofield","position":"NT","number":"98","unit":"Defense"},{"id":"00-0028032","name":"Kenrick Ellis","position":"NT","number":"71","unit":"Defense"},{"id":"00-0031049","name":"Louis Nix","position":"NT","number":"97","unit":"Defense"},{"id":"00-0031241","name":"Devon Kennard","position":"OLB","number":"59","unit":"Defense"},{"id":"00-0028133","name":"J.T. Thomas","position":"OLB","number":"55","unit":"Defense"},{"id":"00-0026832","name":"Jonathan Casillas","position":"OLB","number":"54","unit":"Defense"},{"id":"00-0028620","name":"Mark Herzlich","position":"OLB","number":"94","unit":"Defense"},{"id":"00-0030087","name":"Cooper Taylor","position":"SS","number":"30","unit":"Defense"},{"id":"00-0024796","name":"Craig Dahl","position":"SS","number":"43","unit":"Defense"},{"id":"00-0021940","name":"Josh Brown","position":"K","number":"3","unit":"Special Teams"},{"id":"00-0028496","name":"Danny Aiken","position":"LS","number":"57","unit":"Special Teams"},{"id":"00-0031156","name":"Tyler Ott","position":"LS","number":"69","unit":"Special Teams"},{"id":"00-0025503","name":"Zak DeOssie","position":"LS","number":"51","unit":"Special Teams"},{"id":"00-0030142","name":"Brad Wing","position":"P","number":"9","unit":"Special Teams"}]}