{"team":"PHI","season":2011,"players":[{"id":"00-0021504","name":"Jamaal Jackson","position":"C","number":"67","unit":"Offense"},{"id":"00-0028129","name":"Jason Kelce","position":"C","number":"62","unit":"Offense"},{"id":"00-0026303","name":"Owen Schmitt","position":"FB","number":"32","unit":"Offense"},{"id":"00-0027961","name":"Danny Watkins","position":"G","number":"63","unit":"Offense"},{"id":"00-0023514","name":"Evan Mathis","position":"G","number":"69","unit":"Offense"},{"id":"00-0028099","name":"Julian Vandervelde","position":"G","number":"73","unit":"Offense"},{"id":"00-0020245","name":"Michael Vick","position":"QB","number":"7","unit":"Offense"},{"id":"00-0027722","name":"Mike Kafka","position":"QB","number":"3","unit":"Offense"},{"id":"00-0024218","name":"Vince Young","position":"QB","number":"9","unit":"Offense"},{"id":"00-0028087","name":"Dion Lewis","position":"RB","number":"28","unit":"Offense"},{"id":"00-0027029","name":"LeSean McCoy","position":"RB","number":"25","unit":"Offense"},{"id":"00-0023437","name":"Ronnie Brown","position":"RB","number":"34","unit":"Offense"},{"id":"00-0022531","name":"Jason Peters","position":"T","number":"71","unit":"Offense"},{"id":"00-0026370","name":"King Dunlap","position":"T","number":"65","unit":"Offense"},{"id":"00-0023560","name":"Todd Herremans","position":"T","number":"79","unit":"Offense"},{"id":"00-0024254","name":"Winston Justice","position":"T","number":"74","unit":"Offense"},{"id":"00-0025549","name":"Brent Celek","position":"TE","number":"87","unit":"Offense"},{"id":"00-0027725","name":"Clay Harbor","position":"TE","number":"82","unit":"Offense"},{"id":"00-0027188","name":"Chad Hall","position":"WR","number":"16","unit":"Offense"},{"id":"00-0026189","name":"DeSean Jackson","position":"WR","number":"10","unit":"Offense"},{"id":"00-0024324","name":"Jason Avant","position":"WR","number":"81","unit":"Offense"},{"id":"00-0026995","name":"Jeremy Maclin","position":"WR","number":"18","unit":"Offense"},{"id":"00-0027758","name":"Riley Cooper","position":"WR","number":"14","unit":"Offense"},{"id":"00-0028120","name":"Ronald Johnson","position":"WR","number":"80","unit":"Offense"},{"id":"00-0025438","name":"Steve Smith","position":"WR","number":"11","unit":"Offense"},{"id":"00-0021956","name":"Asante Samuel","position":"CB","number":"22","unit":"Defense"},{"id":"00-0026914","name":"Brandon Hughes","position":"CB","number":"27","unit":"Defense"},{"id":"00-0028028","name":"Curtis Marsh","position":"CB","number":"31","unit":"Defense"},{"id":"00-0026156","name":"Dominique Rodgers-Cromartie","position":"CB","number":"23","unit":"Defense"},{"id":"00-0021654","name":"Joselio Hanson","position":"CB","number":"21","unit":"Defense"},{"id":"00-0022077","name":"Nnamdi Asomugha","position":"CB","number":"24","unit":"Defense"},{"id":"00-0027865","name":"Brandon Graham","position":"DE","number":"54","unit":"Defense"},{"id":"00-0024278","name":"Darryl Tapp","position":"DE","number":"55","unit":"Defense"},{"id":"00-0022695","name":"Jason Babin","position":"DE","number":"93","unit":"Defense"},{"id":"00-0019986","name":"Juqua Parker","position":"DE","number":"75","unit":"Defense"},{"id":"00-0026759","name":"Phillip Hunt","position":"DE","number":"76","unit":"Defense"},{"id":"00-0023579","name":"Trent Cole","position":"DE","number":"58","unit":"Defense"},{"id":"00-0026541","name":"Antonio Dixon","position":"DT","number":"90","unit":"Defense"},{"id":"00-0028424","name":"Cedric Thornton","position":"DT","number":"72","unit":"Defense"},{"id":"00-0021706","name":"Cullen Jenkins","position":"DT","number":"97","unit":"Defense"},{"id":"00-0025553","name":"Derek Landri","position":"DT","number":"94","unit":"Defense"},{"id":"00-0023466","name":"Mike Patterson","position":"DT","number":"98","unit":"Defense"},{"id":"00-0026187","name":"Trevor Laws","position":"DT","number":"91","unit":"Defense"},{"id":"00-0027992","name":"Jaiquawn Jarrett","position":"FS","number":"26","unit":"Defense"},{"id":"00-0027835","name":"Kurt Coleman","position":"FS","number":"42","unit":"Defense"},{"id":"00-0026721","name":"Tom Nelson","position":"FS","number":"49","unit":"Defense"},{"id":"00-0028175","name":"Greg Lloyd","position":"LB","number":"96","unit":"Defense"},{"id":"00-0025719","name":"Akeem Jordan","position":"MLB","number":"56","unit":"Defense"},{"id":"00-0028054","name":"Casey Matthews","position":"MLB","number":"50","unit":"Defense"},{"id":"00-0028131","name":"Brian Rolle","position":"OLB","number":"59","unit":"Defense"},{"id":"00-0027814","name":"Jamar Chaney","position":"OLB","number":"51","unit":"Defense"},{"id":"00-0027721","name":"Keenan Clayton","position":"OLB","number":"57","unit":"Defense"},{"id":"00-0026951","name":"Moise Fokou","position":"OLB","number":"53","unit":"Defense"},{"id":"00-0026578","name":"Colt Anderson","position":"SS","number":"30","unit":"Defense"},{"id":"00-0024442","name":"Jarrad Page","position":"SS","number":"41","unit":"Defense"},{"id":"00-0027652","name":"Nate Allen","position":"SS","number":"29","unit":"Defense"},{"id":"00-0028058","name":"Alex Henery","position":"K","number":"6","unit":"Special Teams"},{"id":"00-0021451","name":"Jon Dorenbos","position":"LS","number":"46","unit":"Special Teams"},{"id":"00-0028427","name":"Chas Henry","position":"P","number":"8","unit":"Special Teams"}]}