{"team":"ATL","season":"2015-16","players":[{"id":201952,"name":"Jeff Teague","position":"G","number":"0","ppg":0.0,"isLowScorer":false},{"id":200794,"name":"Paul Millsap","position":"F","number":"4","ppg":0.0,"isLowScorer":false},{"id":203501,"name":"Tim Hardaway Jr.","position":"G","number":"10","ppg":0.0,"isLowScorer":false},{"id":201168,"name":"Tiago Splitter","position":"C-F","number":"11","ppg":0.0,"isLowScorer":false},{"id":2550,"name":"Kirk Hinrich","position":"G","number":"12","ppg":0.0,"isLowScorer":false},{"id":203934,"name":"Lamar Patterson","position":"G-F","number":"13","ppg":0.0,"isLowScorer":false},{"id":201143,"name":"Al Horford","position":"C-F","number":"15","ppg":0.0,"isLowScorer":false},{"id":203471,"name":"Dennis Schröder","position":"G","number":"17","ppg":0.0,"isLowScorer":false},{"id":204002,"name":"Edy Tavares","position":"C","number":"22","ppg":0.0,"isLowScorer":false},{"id":203145,"name":"Kent Bazemore","position":"F-G","number":"24","ppg":0.0,"isLowScorer":false},{"id":200757,"name":"Thabo Sefolosha","position":"F","number":"25","ppg":0.0,"isLowScorer":false},{"id":2594,"name":"Kyle Korver","position":"G","number":"26","ppg":0.0,"isLowScorer":false},{"id":203488,"name":"Mike Muscala","position":"F-C","number":"31","ppg":0.0,"isLowScorer":false},{"id":203118,"name":"Mike Scott","position":"F","number":"32","ppg":0.0,"isLowScorer":false},{"id":2743,"name":"Kris Humphries","position":"F","number":"43","ppg":0.0,"isLowScorer":false}]}