{"team":"OKC","season":"2011-12","players":[{"id":201566,"name":"Russell Westbrook","position":"G","number":"0","ppg":0.0,"isLowScorer":false},{"id":200757,"name":"Thabo Sefolosha","position":"G","number":"2","ppg":0.0,"isLowScorer":false},{"id":2555,"name":"Nick Collison","position":"F-C","number":"4","ppg":0.0,"isLowScorer":false},{"id":2570,"name":"Kendrick Perkins","position":"C","number":"5","ppg":0.0,"isLowScorer":false},{"id":201953,"name":"Eric Maynor","position":"G","number":"6","ppg":0.0,"isLowScorer":false},{"id":2767,"name":"Royal Ivey","position":"G","number":"7","ppg":0.0,"isLowScorer":false},{"id":1737,"name":"Nazr Mohammed","position":"C","number":"8","ppg":0.0,"isLowScorer":false},{"id":201586,"name":"Serge Ibaka","position":"F-C","number":"9","ppg":0.0,"isLowScorer":false},{"id":202351,"name":"Lazar Hayward","position":"F","number":"11","ppg":0.0,"isLowScorer":false},{"id":201935,"name":"James Harden","position":"G","number":"13","ppg":0.0,"isLowScorer":false},{"id":201161,"name":"Daequan Cook","position":"G","number":"14","ppg":0.0,"isLowScorer":false},{"id":202704,"name":"Reggie Jackson","position":"G","number":"15","ppg":0.0,"isLowScorer":false},{"id":201142,"name":"Kevin Durant","position":"F","number":"35","ppg":0.0,"isLowScorer":false},{"id":965,"name":"Derek Fisher","position":"G","number":"37","ppg":0.0,"isLowScorer":false},{"id":202332,"name":"Cole Aldrich","position":"C","number":"45","ppg":0.0,"isLowScorer":false}]}