{"team":"PHI","season":"2015-16","players":[{"id":203477,"name":"Isaiah Canaan","position":"G","number":"0","ppg":0.0,"isLowScorer":false},{"id":202397,"name":"Ish Smith","position":"G","number":"1","ppg":0.0,"isLowScorer":false},{"id":203457,"name":"Nerlens Noel","position":"F-C","number":"4","ppg":0.0,"isLowScorer":false},{"id":203088,"name":"Kendall Marshall","position":"G","number":"5","ppg":0.0,"isLowScorer":false},{"id":201171,"name":"Carl Landry","position":"F","number":"7","ppg":0.0,"isLowScorer":false},{"id":1626143,"name":"Jahlil Okafor","position":"C","number":"8","ppg":0.0,"isLowScorer":false},{"id":203917,"name":"Nik Stauskas","position":"G","number":"11","ppg":0.0,"isLowScorer":false},{"id":204456,"name":"T.J. McConnell","position":"G","number":"12","ppg":0.0,"isLowScorer":false},{"id":203954,"name":"Joel Embiid","position":"C","number":"21","ppg":0.0,"isLowScorer":false},{"id":1626158,"name":"Richaun Holmes","position":"F","number":"22","ppg":0.0,"isLowScorer":false},{"id":203138,"name":"Hollis Thompson","position":"G-F","number":"31","ppg":0.0,"isLowScorer":false},{"id":203496,"name":"Robert Covington","position":"F","number":"33","ppg":0.0,"isLowScorer":false},{"id":1626174,"name":"Christian Wood","position":"F","number":"35","ppg":0.0,"isLowScorer":false},{"id":203924,"name":"Jerami Grant","position":"F","number":"39","ppg":0.0,"isLowScorer":false},{"id":1882,"name":"Elton Brand","position":"F","number":"42","ppg":0.0,"isLowScorer":false}]}