{"team":"PHX","season":"2002-03","players":[{"id":753,"name":"Randy Brown","position":"G","number":"0","ppg":0.0,"isLowScorer":false},{"id":358,"name":"Anfernee Hardaway","position":"G-F","number":"1","ppg":0.0,"isLowScorer":false},{"id":2207,"name":"Joe Johnson","position":"G-F","number":"2","ppg":0.0,"isLowScorer":false},{"id":950,"name":"Stephon Marbury","position":"G","number":"3","ppg":0.0,"isLowScorer":false},{"id":2228,"name":"Alton Ford","position":"F","number":"4","ppg":0.0,"isLowScorer":false},{"id":924,"name":"Anthony Goldwire","position":"G","number":"10","ppg":0.0,"isLowScorer":false},{"id":2486,"name":"Maurice Baker","position":"G","number":"12","ppg":0.0,"isLowScorer":false},{"id":2061,"name":"Dan Langhi","position":"F","number":"14","ppg":0.0,"isLowScorer":false},{"id":2418,"name":"Casey Jacobsen","position":"G-F","number":"23","ppg":0.0,"isLowScorer":false},{"id":339,"name":"Tom Gugliotta","position":"F","number":"24","ppg":0.0,"isLowScorer":false},{"id":2054,"name":"Jake Tsakalidis","position":"C","number":"25","ppg":0.0,"isLowScorer":false},{"id":1890,"name":"Shawn Marion","position":"F","number":"31","ppg":0.0,"isLowScorer":false},{"id":2405,"name":"Amar'e Stoudemire","position":"F","number":"32","ppg":0.0,"isLowScorer":false},{"id":2063,"name":"Jake Voskuhl","position":"C","number":"43","ppg":0.0,"isLowScorer":false},{"id":448,"name":"Bo Outlaw","position":"F","number":"45","ppg":0.0,"isLowScorer":false},{"id":281,"name":"Scott Williams","position":"F-C","number":"47","ppg":0.0,"isLowScorer":false}]}